LICENSE
README.md
setup.cfg
setup.py
docs/README.md
pywarping/__init__.py
pywarping/actions.py
pywarping/base.py
pywarping/cli.py
pywarping/data.py
pywarping/detect.py
pywarping/reference.py
pywarping/utils.py
pywarping/visualization.py
pywarping.egg-info/PKG-INFO
pywarping.egg-info/SOURCES.txt
pywarping.egg-info/dependency_links.txt
pywarping.egg-info/entry_points.txt
pywarping.egg-info/requires.txt
pywarping.egg-info/top_level.txt