Metadata-Version: 2.1
Name: pywarping
Version: 0.2
Summary: Automated face warping tool
Home-page: https://github.com/dopevog/pywarping
Author: Vedant Kothari
Author-email: dopevog@gmail.com
License: MIT
Project-URL: Bug Tracker, https://github.com/dopevog/pywarping/issues
Project-URL: Documentation, https://pywarping.readthedocs.io
Project-URL: Source Code, https://github.com/dopevog/pywarping
Platform: UNKNOWN
Classifier: License :: OSI Approved :: MIT License
Classifier: Intended Audience :: Science/Research
Classifier: Intended Audience :: Developers
Classifier: Programming Language :: C
Classifier: Programming Language :: Python
Classifier: Topic :: Software Development
Classifier: Topic :: Scientific/Engineering
Classifier: Operating System :: Microsoft :: Windows
Classifier: Operating System :: POSIX
Classifier: Operating System :: Unix
Classifier: Operating System :: MacOS
Classifier: Programming Language :: Python :: 3
Classifier: Programming Language :: Python :: 3.5
Classifier: Programming Language :: Python :: 3.6
Classifier: Programming Language :: Python :: 3.7
Classifier: Programming Language :: Python :: Implementation :: CPython
Requires-Python: >=3.5
Provides-Extra: dev
Provides-Extra: docs
